dgNN
fused_edgeconv
fused_gatconv
fused_gmmconv
mhsddmm
mhtranspose
